AUTHORS
CHANGELOG
FAQ
INSTALL
LICENSE
MANIFEST.in
NEWS
README
README.rst
THANKS
TODO
requirements.txt
setup.py
wave.txt
docs/Makefile
docs/README.rst
docs/about.rst
docs/changelog.rst
docs/changelog.rst~
docs/conf.py
docs/conf.py~
docs/example.rst
docs/example.rst~
docs/index.rst
docs/index.rst~
docs/index_latex.rst
docs/install.rst
docs/install.rst~
docs/license.rst
docs/make.bat
docs/modules.rst
docs/programs.rst
docs/programs.rst~
docs/todo.rst
docs/usage.rst
docs/usage.rst~
docs/_images/exquires-logo.png
docs/_static/exquires-favicon.ico
docs/_theme/exquires/theme.conf
docs/_theme/exquires/static/exquires.css_t
exquires/__init__.py
exquires/aggregate.py
exquires/compare.py
exquires/correlate.py
exquires/database.py
exquires/new.py
exquires/operations.py
exquires/parsing.py
exquires/progress.py
exquires/report.py
exquires/run.py
exquires/sRGB_IEC61966-2-1_black_scaled.icc
exquires/stats.py
exquires/tools.py
exquires/update.py
exquires/wave.tif
exquires.egg-info/PKG-INFO
exquires.egg-info/SOURCES.txt
exquires.egg-info/dependency_links.txt
exquires.egg-info/entry_points.txt
exquires.egg-info/requires.txt
exquires.egg-info/top_level.txt
exquires/examples/README.rst
exquires/examples/nohalo.cpp