Metadata-Version: 1.1
Name: exquires
Version: 0.9.9.3
Summary: EXQUIRES (EXtensible QUantitative Image RESampling) test suite
Home-page: http://exquires.ca
Author: Adam Turcotte
Author-email: adam.turcotte@gmail.com
License: BSD 2-Clause (http://www.opensource.org/licenses/bsd-license.php)
Keywords: image,reconstruction,enlargement,upsampling,test,testing
Platform: UNKNOWN
Classifier: Development Status :: 4 - Beta
Classifier: License :: OSI Approved :: BSD License
Classifier: Operating System :: OS Independent
Classifier: Programming Language :: Python
Classifier: Programming Language :: Python :: 2.7
Classifier: Programming Language :: Python :: 3
Classifier: Topic :: Multimedia :: Graphics
Classifier: Topic :: Software Development :: Testing
